epoch.py
epochcli.py
epochclient.py
epochplugins/__init__.py
epochplugins/cluster.py
epochplugins/filter_topologies.py
epochplugins/runs.py
epochplugins/topology.py
epochutils.py
epoch_cli-0.0.3.dist-info/METADATA
epoch_cli-0.0.3.dist-info/WHEEL
epoch_cli-0.0.3.dist-info/entry_points.txt
epoch_cli-0.0.3.dist-info/RECORD
