Metadata-Version: 2.1
Name: epoch-cli
Version: 0.0.3
Summary: Command line interface for Epoch task scheduler
Home-page: https://github.com/PhonePe/epoch-cli
License: Apache-2.0
Keywords: container,docker,podman,distributed-systems,container-orchestrator
Author: Shubhransh Jagota
Author-email: mailtoshubhransh@gmail.com
Maintainer: Tushar Naik
Maintainer-email: tushar.knaik@gmail.com
Requires-Python: >=3.9,<4.0
Classifier: Development Status :: 5 - Production/Stable
Classifier: Intended Audience :: Developers
Classifier: Intended Audience :: System Administrators
Classifier: License :: OSI Approved :: Apache Software License
Classifier: Programming Language :: Python :: 3
Classifier: Programming Language :: Python :: 3.9
Classifier: Programming Language :: Python :: 3.10
Classifier: Programming Language :: Python :: 3.11
Classifier: Programming Language :: Python :: 3.12
Classifier: Topic :: System :: Clustering
Classifier: Topic :: System :: Distributed Computing
Requires-Dist: Requests (==2.31.0)
Requires-Dist: tabulate (==0.9.0)
Requires-Dist: tenacity (==8.2.3)
Requires-Dist: urllib3 (==1.26.5)
Project-URL: Repository, https://github.com/PhonePe/epoch-cli
